Metadata-Version: 1.0
Name: Philips
Version: 1.0.0
Summary: A bunch of utility functions created during classroom practice
Home-page: UNKNOWN
Author: Vinod
Author-email: vinod@vinod.co
License: UNKNOWN
Platform: UNKNOWN
